{
    "Version": 3,
    "Meta": {
        "Duration": 3.333,
        "Fps": 30.0,
        "Loop": true,
        "AreBeziersRestricted": true,
        "CurveCount": 139,
        "TotalSegmentCount": 147,
        "TotalPointCount": 304,
        "UserDataCount": 1,
        "TotalUserDataSize": 0
    },
    "Curves": [
        {
            "Target": "Model",
            "Id": "Opacity",
            "Segments": [
                0,
                1,
                0,
                3.333,
                1
            ]
        },
        {
            "Target": "Parameter",
            "Id": "ParamBodyAngleY",
            "Segments": [
                0,
                -0.256,
                1,
                0.622,
                0.19,
                1.245,
                0.2,
                1.867,
                0.2,
                1,
                2.356,
                0.2,
                2.844,
                -0.236,
                3.333,
                -0.255
            ]
        },
        {
            "Target": "Parameter",
            "Id": "ParamBreath",
            "Segments": [
                0,
                0,
                0,
                1.733,
                0.5,
                1,
                2.266,
                0.5,
                2.8,
                0.02,
                3.333,
                0.001
            ]
        },
        {
            "Target": "Parameter",
            "Id": "ParamShoulderR",
            "Segments": [
                0,
                -10,
                0,
                1.833,
                -6,
                1,
                2.333,
                -6,
                2.833,
                -9.828,
                3.333,
                -9.994
            ]
        },
        {
            "Target": "Parameter",
            "Id": "ParamArmupperR",
            "Segments": [
                0,
                -46,
                0,
                1.867,
                -45.7,
                1,
                2.356,
                -45.7,
                2.844,
                -45.987,
                3.333,
                -46
            ]
        },
        {
            "Target": "Parameter",
            "Id": "ParamArmforeR",
            "Segments": [
                0,
                2,
                0,
                1.9,
                2.2,
                1,
                2.378,
                2.2,
                2.855,
                2.009,
                3.333,
                2
            ]
        },
        {
            "Target": "Parameter",
            "Id": "ParamShoulderL",
            "Segments": [
                0,
                -8,
                0,
                1.833,
                -4,
                1,
                2.333,
                -4,
                2.833,
                -7.828,
                3.333,
                -7.994
            ]
        },
        {
            "Target": "Parameter",
            "Id": "ParamArmupperL",
            "Segments": [
                0,
                -44,
                0,
                1.867,
                -43.7,
                1,
                2.356,
                -43.7,
                2.844,
                -43.987,
                3.333,
                -44
            ]
        },
        {
            "Target": "Parameter",
            "Id": "ParamArmforeL",
            "Segments": [
                0,
                1.5,
                0,
                1.9,
                1.7,
                1,
                2.378,
                1.7,
                2.855,
                1.509,
                3.333,
                1.5
            ]
        },
        {
            "Target": "Parameter",
            "Id": "ParamAngleX",
            "Segments": [
                0,
                -30,
                0,
                3.333,
                -30
            ]
        },
        {
            "Target": "Parameter",
            "Id": "ParamAngleY",
            "Segments": [
                0,
                -0.514,
                0,
                3.333,
                -0.514
            ]
        },
        {
            "Target": "Parameter",
            "Id": "ParamAngleZ",
            "Segments": [
                0,
                -9.871,
                0,
                3.333,
                -9.871
            ]
        },
        {
            "Target": "Parameter",
            "Id": "ParamEyeLOpen",
            "Segments": [
                0,
                1,
                0,
                3.333,
                1
            ]
        },
        {
            "Target": "Parameter",
            "Id": "ParamEyeLSmile",
            "Segments": [
                0,
                0,
                0,
                3.333,
                0
            ]
        },
        {
            "Target": "Parameter",
            "Id": "ParamEyeForm_L",
            "Segments": [
                0,
                0,
                0,
                3.333,
                0
            ]
        },
        {
            "Target": "Parameter",
            "Id": "ParamEyeROpen",
            "Segments": [
                0,
                1,
                0,
                3.333,
                1
            ]
        },
        {
            "Target": "Parameter",
            "Id": "ParamEyeRSmile",
            "Segments": [
                0,
                0,
                0,
                3.333,
                0
            ]
        },
        {
            "Target": "Parameter",
            "Id": "ParamEyeForm_R",
            "Segments": [
                0,
                0,
                0,
                3.333,
                0
            ]
        },
        {
            "Target": "Parameter",
            "Id": "ParamEyeBallX",
            "Segments": [
                0,
                0.3,
                0,
                3.333,
                0.3
            ]
        },
        {
            "Target": "Parameter",
            "Id": "ParamEyeBallY",
            "Segments": [
                0,
                0.1,
                0,
                3.333,
                0.1
            ]
        },
        {
            "Target": "Parameter",
            "Id": "ParamEyeScale",
            "Segments": [
                0,
                0,
                0,
                3.333,
                0
            ]
        },
        {
            "Target": "Parameter",
            "Id": "Param_tear_display",
            "Segments": [
                0,
                0,
                0,
                3.333,
                0
            ]
        },
        {
            "Target": "Parameter",
            "Id": "ParamBrowLY",
            "Segments": [
                0,
                0,
                0,
                3.333,
                0
            ]
        },
        {
            "Target": "Parameter",
            "Id": "ParamBrowRY",
            "Segments": [
                0,
                0,
                0,
                3.333,
                0
            ]
        },
        {
            "Target": "Parameter",
            "Id": "ParamBrowLX",
            "Segments": [
                0,
                0,
                0,
                3.333,
                0
            ]
        },
        {
            "Target": "Parameter",
            "Id": "ParamBrowRX",
            "Segments": [
                0,
                0,
                0,
                3.333,
                0
            ]
        },
        {
            "Target": "Parameter",
            "Id": "ParamBrowLAngle",
            "Segments": [
                0,
                0,
                0,
                3.333,
                0
            ]
        },
        {
            "Target": "Parameter",
            "Id": "ParamBrowRAngle",
            "Segments": [
                0,
                0,
                0,
                3.333,
                0
            ]
        },
        {
            "Target": "Parameter",
            "Id": "ParamBrowLForm",
            "Segments": [
                0,
                0,
                0,
                3.333,
                0
            ]
        },
        {
            "Target": "Parameter",
            "Id": "ParamBrowRForm",
            "Segments": [
                0,
                0,
                0,
                3.333,
                0
            ]
        },
        {
            "Target": "Parameter",
            "Id": "ParamMouthOpenY",
            "Segments": [
                0,
                0,
                0,
                3.333,
                0
            ]
        },
        {
            "Target": "Parameter",
            "Id": "Param_mouth_form01",
            "Segments": [
                0,
                0,
                0,
                3.333,
                0
            ]
        },
        {
            "Target": "Parameter",
            "Id": "Param_mouth_form02",
            "Segments": [
                0,
                0,
                0,
                3.333,
                0
            ]
        },
        {
            "Target": "Parameter",
            "Id": "ParamTooth",
            "Segments": [
                0,
                0,
                0,
                3.333,
                0
            ]
        },
        {
            "Target": "Parameter",
            "Id": "ParamCheek",
            "Segments": [
                0,
                1,
                0,
                3.333,
                1
            ]
        },
        {
            "Target": "Parameter",
            "Id": "ParamSweat",
            "Segments": [
                0,
                0,
                0,
                3.333,
                0
            ]
        },
        {
            "Target": "Parameter",
            "Id": "ParamBodyAngleX",
            "Segments": [
                0,
                -7.995,
                0,
                3.333,
                -7.995
            ]
        },
        {
            "Target": "Parameter",
            "Id": "ParamBodyAngleZ",
            "Segments": [
                0,
                -1,
                0,
                3.333,
                -1
            ]
        },
        {
            "Target": "Parameter",
            "Id": "ParamUpperbody",
            "Segments": [
                0,
                0,
                0,
                3.333,
                0
            ]
        },
        {
            "Target": "Parameter",
            "Id": "doubleX",
            "Segments": [
                0,
                4,
                0,
                3.333,
                4
            ]
        },
        {
            "Target": "Parameter",
            "Id": "Param12",
            "Segments": [
                0,
                0,
                0,
                3.333,
                0
            ]
        },
        {
            "Target": "Parameter",
            "Id": "Param13",
            "Segments": [
                0,
                0,
                0,
                3.333,
                0
            ]
        },
        {
            "Target": "Parameter",
            "Id": "Param6",
            "Segments": [
                0,
                -28.709,
                0,
                3.333,
                -28.709
            ]
        },
        {
            "Target": "Parameter",
            "Id": "Param5",
            "Segments": [
                0,
                -6.123,
                0,
                3.333,
                -6.123
            ]
        },
        {
            "Target": "Parameter",
            "Id": "Param9",
            "Segments": [
                0,
                -20.154,
                0,
                3.333,
                -20.154
            ]
        },
        {
            "Target": "Parameter",
            "Id": "ParamArmupperR_02",
            "Segments": [
                0,
                0,
                0,
                3.333,
                0
            ]
        },
        {
            "Target": "Parameter",
            "Id": "ParamArmforeR_02",
            "Segments": [
                0,
                0,
                0,
                3.333,
                0
            ]
        },
        {
            "Target": "Parameter",
            "Id": "ParamHandR",
            "Segments": [
                0,
                -3,
                0,
                3.333,
                -3
            ]
        },
        {
            "Target": "Parameter",
            "Id": "ParamHandR_01",
            "Segments": [
                0,
                1,
                0,
                3.333,
                1
            ]
        },
        {
            "Target": "Parameter",
            "Id": "ParamHandR_02",
            "Segments": [
                0,
                0,
                0,
                3.333,
                0
            ]
        },
        {
            "Target": "Parameter",
            "Id": "Param3",
            "Segments": [
                0,
                0,
                0,
                3.333,
                0
            ]
        },
        {
            "Target": "Parameter",
            "Id": "ParamHandR_03",
            "Segments": [
                0,
                0,
                0,
                3.333,
                0
            ]
        },
        {
            "Target": "Parameter",
            "Id": "ParamHandR_04",
            "Segments": [
                0,
                0,
                0,
                3.333,
                0
            ]
        },
        {
            "Target": "Parameter",
            "Id": "ParamHandR_05",
            "Segments": [
                0,
                0,
                0,
                3.333,
                0
            ]
        },
        {
            "Target": "Parameter",
            "Id": "ParamHandR_06",
            "Segments": [
                0,
                0,
                0,
                3.333,
                0
            ]
        },
        {
            "Target": "Parameter",
            "Id": "ParamHandR_07",
            "Segments": [
                0,
                0,
                0,
                3.333,
                0
            ]
        },
        {
            "Target": "Parameter",
            "Id": "ParamHandR_08",
            "Segments": [
                0,
                0,
                0,
                3.333,
                0
            ]
        },
        {
            "Target": "Parameter",
            "Id": "ParamHandR_09",
            "Segments": [
                0,
                0,
                0,
                3.333,
                0
            ]
        },
        {
            "Target": "Parameter",
            "Id": "Param2",
            "Segments": [
                0,
                0,
                0,
                3.333,
                0
            ]
        },
        {
            "Target": "Parameter",
            "Id": "Param11",
            "Segments": [
                0,
                0,
                0,
                3.333,
                0
            ]
        },
        {
            "Target": "Parameter",
            "Id": "ParamArmupperL_02",
            "Segments": [
                0,
                0,
                0,
                3.333,
                0
            ]
        },
        {
            "Target": "Parameter",
            "Id": "ParamArmforeL_02",
            "Segments": [
                0,
                0,
                0,
                3.333,
                0
            ]
        },
        {
            "Target": "Parameter",
            "Id": "ParamHandL",
            "Segments": [
                0,
                -3,
                0,
                3.333,
                -3
            ]
        },
        {
            "Target": "Parameter",
            "Id": "ParamHandL_01",
            "Segments": [
                0,
                1,
                0,
                3.333,
                1
            ]
        },
        {
            "Target": "Parameter",
            "Id": "ParamHandL_02",
            "Segments": [
                0,
                0,
                0,
                3.333,
                0
            ]
        },
        {
            "Target": "Parameter",
            "Id": "ParamHandL_03",
            "Segments": [
                0,
                0,
                0,
                3.333,
                0
            ]
        },
        {
            "Target": "Parameter",
            "Id": "ParamHandL_04",
            "Segments": [
                0,
                0,
                0,
                3.333,
                0
            ]
        },
        {
            "Target": "Parameter",
            "Id": "ParamHandL_05",
            "Segments": [
                0,
                0,
                0,
                3.333,
                0
            ]
        },
        {
            "Target": "Parameter",
            "Id": "ParamHandL_06",
            "Segments": [
                0,
                0,
                0,
                3.333,
                0
            ]
        },
        {
            "Target": "Parameter",
            "Id": "ParamHandL_07",
            "Segments": [
                0,
                0,
                0,
                3.333,
                0
            ]
        },
        {
            "Target": "Parameter",
            "Id": "ParamHandL_08",
            "Segments": [
                0,
                0,
                0,
                3.333,
                0
            ]
        },
        {
            "Target": "Parameter",
            "Id": "ParamHandL_09",
            "Segments": [
                0,
                0,
                0,
                3.333,
                0
            ]
        },
        {
            "Target": "Parameter",
            "Id": "Param4",
            "Segments": [
                0,
                -4.47,
                0,
                3.333,
                -4.47
            ]
        },
        {
            "Target": "Parameter",
            "Id": "Param7",
            "Segments": [
                0,
                6.009,
                0,
                3.333,
                6.009
            ]
        },
        {
            "Target": "Parameter",
            "Id": "Param_Ring_angle",
            "Segments": [
                0,
                2.596,
                0,
                3.333,
                2.596
            ]
        },
        {
            "Target": "Parameter",
            "Id": "Param",
            "Segments": [
                0,
                0,
                0,
                3.333,
                0
            ]
        },
        {
            "Target": "Parameter",
            "Id": "Param_reg_L",
            "Segments": [
                0,
                -9,
                0,
                3.333,
                -9
            ]
        },
        {
            "Target": "Parameter",
            "Id": "Param_reg_R",
            "Segments": [
                0,
                -6.271,
                0,
                3.333,
                -6.271
            ]
        },
        {
            "Target": "Parameter",
            "Id": "Param_knee_L",
            "Segments": [
                0,
                3,
                0,
                3.333,
                3
            ]
        },
        {
            "Target": "Parameter",
            "Id": "Param_knee_R",
            "Segments": [
                0,
                5,
                0,
                3.333,
                5
            ]
        },
        {
            "Target": "Parameter",
            "Id": "Param_ankle_L",
            "Segments": [
                0,
                6,
                0,
                3.333,
                6
            ]
        },
        {
            "Target": "Parameter",
            "Id": "Param_ankle_R",
            "Segments": [
                0,
                -6,
                0,
                3.333,
                -6
            ]
        },
        {
            "Target": "Parameter",
            "Id": "ParamHairFront",
            "Segments": [
                0,
                0,
                0,
                3.333,
                0
            ]
        },
        {
            "Target": "Parameter",
            "Id": "ParamHairSide",
            "Segments": [
                0,
                0,
                0,
                3.333,
                0
            ]
        },
        {
            "Target": "Parameter",
            "Id": "ParamHairBack2",
            "Segments": [
                0,
                0,
                0,
                3.333,
                0
            ]
        },
        {
            "Target": "Parameter",
            "Id": "ParamHairBack3",
            "Segments": [
                0,
                0,
                0,
                3.333,
                0
            ]
        },
        {
            "Target": "Parameter",
            "Id": "ParamHairF",
            "Segments": [
                0,
                0,
                0,
                3.333,
                0
            ]
        },
        {
            "Target": "Parameter",
            "Id": "ParamBustY",
            "Segments": [
                0,
                0,
                0,
                3.333,
                0
            ]
        },
        {
            "Target": "Parameter",
            "Id": "ParamHairDeco1",
            "Segments": [
                0,
                0,
                0,
                3.333,
                0
            ]
        },
        {
            "Target": "Parameter",
            "Id": "ParamNeckDeco2",
            "Segments": [
                0,
                0,
                0,
                3.333,
                0
            ]
        },
        {
            "Target": "Parameter",
            "Id": "Param8",
            "Segments": [
                0,
                0,
                0,
                3.333,
                0
            ]
        },
        {
            "Target": "Parameter",
            "Id": "Param10",
            "Segments": [
                0,
                0,
                0,
                3.333,
                0
            ]
        },
        {
            "Target": "Parameter",
            "Id": "Param_head_size",
            "Segments": [
                0,
                -0.4,
                0,
                3.333,
                -0.4
            ]
        },
        {
            "Target": "Parameter",
            "Id": "ParamSize",
            "Segments": [
                0,
                0,
                0,
                3.333,
                0
            ]
        },
        {
            "Target": "Parameter",
            "Id": "Param_vertical",
            "Segments": [
                0,
                0,
                0,
                3.333,
                0
            ]
        },
        {
            "Target": "Parameter",
            "Id": "Param_Neck_set",
            "Segments": [
                0,
                -5,
                0,
                3.333,
                -5
            ]
        },
        {
            "Target": "Parameter",
            "Id": "Param_horizontal",
            "Segments": [
                0,
                0,
                0,
                3.333,
                0
            ]
        },
        {
            "Target": "Parameter",
            "Id": "Param_allrotation",
            "Segments": [
                0,
                0,
                0,
                3.333,
                0
            ]
        },
        {
            "Target": "PartOpacity",
            "Id": "Part_core",
            "Segments": [
                0,
                1,
                2,
                3.33,
                1
            ]
        },
        {
            "Target": "PartOpacity",
            "Id": "Part_neck",
            "Segments": [
                0,
                1,
                2,
                3.33,
                1
            ]
        },
        {
            "Target": "PartOpacity",
            "Id": "Part_head_002",
            "Segments": [
                0,
                1,
                2,
                3.33,
                1
            ]
        },
        {
            "Target": "PartOpacity",
            "Id": "Part18",
            "Segments": [
                0,
                1,
                2,
                3.33,
                1
            ]
        },
        {
            "Target": "PartOpacity",
            "Id": "Part_face2",
            "Segments": [
                0,
                1,
                2,
                3.33,
                1
            ]
        },
        {
            "Target": "PartOpacity",
            "Id": "Part19",
            "Segments": [
                0,
                1,
                2,
                3.33,
                1
            ]
        },
        {
            "Target": "PartOpacity",
            "Id": "Part20",
            "Segments": [
                0,
                1,
                2,
                3.33,
                1
            ]
        },
        {
            "Target": "PartOpacity",
            "Id": "Part_eye_R2",
            "Segments": [
                0,
                1,
                2,
                3.33,
                1
            ]
        },
        {
            "Target": "PartOpacity",
            "Id": "Part_eye_L2",
            "Segments": [
                0,
                1,
                2,
                3.33,
                1
            ]
        },
        {
            "Target": "PartOpacity",
            "Id": "Part22",
            "Segments": [
                0,
                1,
                2,
                3.33,
                1
            ]
        },
        {
            "Target": "PartOpacity",
            "Id": "Part_eyebrows2",
            "Segments": [
                0,
                1,
                2,
                3.33,
                1
            ]
        },
        {
            "Target": "PartOpacity",
            "Id": "Part_cheek2",
            "Segments": [
                0,
                1,
                2,
                3.33,
                1
            ]
        },
        {
            "Target": "PartOpacity",
            "Id": "Part_ear2",
            "Segments": [
                0,
                1,
                2,
                3.33,
                1
            ]
        },
        {
            "Target": "PartOpacity",
            "Id": "Part_nose2",
            "Segments": [
                0,
                1,
                2,
                3.33,
                1
            ]
        },
        {
            "Target": "PartOpacity",
            "Id": "Part23",
            "Segments": [
                0,
                1,
                2,
                3.33,
                1
            ]
        },
        {
            "Target": "PartOpacity",
            "Id": "Part24",
            "Segments": [
                0,
                1,
                2,
                3.33,
                1
            ]
        },
        {
            "Target": "PartOpacity",
            "Id": "Part_hair_front2",
            "Segments": [
                0,
                1,
                2,
                3.33,
                1
            ]
        },
        {
            "Target": "PartOpacity",
            "Id": "Part_hair_side2",
            "Segments": [
                0,
                1,
                2,
                3.33,
                1
            ]
        },
        {
            "Target": "PartOpacity",
            "Id": "Part_hair_back2",
            "Segments": [
                0,
                1,
                2,
                3.33,
                1
            ]
        },
        {
            "Target": "PartOpacity",
            "Id": "Part16",
            "Segments": [
                0,
                1,
                2,
                3.33,
                1
            ]
        },
        {
            "Target": "PartOpacity",
            "Id": "Part_body2_002",
            "Segments": [
                0,
                1,
                2,
                3.33,
                1
            ]
        },
        {
            "Target": "PartOpacity",
            "Id": "Part",
            "Segments": [
                0,
                1,
                2,
                3.33,
                1
            ]
        },
        {
            "Target": "PartOpacity",
            "Id": "Part_reg_002",
            "Segments": [
                0,
                1,
                2,
                3.33,
                1
            ]
        },
        {
            "Target": "PartOpacity",
            "Id": "Part_reg_L2",
            "Segments": [
                0,
                1,
                2,
                3.33,
                1
            ]
        },
        {
            "Target": "PartOpacity",
            "Id": "Part12",
            "Segments": [
                0,
                1,
                2,
                3.33,
                1
            ]
        },
        {
            "Target": "PartOpacity",
            "Id": "Part14",
            "Segments": [
                0,
                1,
                2,
                3.33,
                1
            ]
        },
        {
            "Target": "PartOpacity",
            "Id": "Part_reg_R2",
            "Segments": [
                0,
                1,
                2,
                3.33,
                1
            ]
        },
        {
            "Target": "PartOpacity",
            "Id": "Part10",
            "Segments": [
                0,
                1,
                2,
                3.33,
                1
            ]
        },
        {
            "Target": "PartOpacity",
            "Id": "Part11",
            "Segments": [
                0,
                1,
                2,
                3.33,
                1
            ]
        },
        {
            "Target": "PartOpacity",
            "Id": "Part_arm_A_L_002",
            "Segments": [
                0,
                0,
                2,
                3.33,
                0
            ]
        },
        {
            "Target": "PartOpacity",
            "Id": "Part35",
            "Segments": [
                0,
                1,
                2,
                3.33,
                1
            ]
        },
        {
            "Target": "PartOpacity",
            "Id": "Part36",
            "Segments": [
                0,
                1,
                2,
                3.33,
                1
            ]
        },
        {
            "Target": "PartOpacity",
            "Id": "Part_arm_A_R_002",
            "Segments": [
                0,
                0,
                2,
                3.33,
                0
            ]
        },
        {
            "Target": "PartOpacity",
            "Id": "Part33",
            "Segments": [
                0,
                1,
                2,
                3.33,
                1
            ]
        },
        {
            "Target": "PartOpacity",
            "Id": "Part34",
            "Segments": [
                0,
                1,
                2,
                3.33,
                1
            ]
        },
        {
            "Target": "PartOpacity",
            "Id": "Part_arm_B_L_002",
            "Segments": [
                0,
                1,
                2,
                3.33,
                1
            ]
        },
        {
            "Target": "PartOpacity",
            "Id": "Part37",
            "Segments": [
                0,
                1,
                2,
                3.33,
                1
            ]
        },
        {
            "Target": "PartOpacity",
            "Id": "Part38",
            "Segments": [
                0,
                1,
                2,
                3.33,
                1
            ]
        },
        {
            "Target": "PartOpacity",
            "Id": "Part_arm_B_R_002",
            "Segments": [
                0,
                1,
                2,
                3.33,
                1
            ]
        },
        {
            "Target": "PartOpacity",
            "Id": "Part39",
            "Segments": [
                0,
                1,
                2,
                3.33,
                1
            ]
        },
        {
            "Target": "PartOpacity",
            "Id": "Part40",
            "Segments": [
                0,
                1,
                2,
                3.33,
                1
            ]
        }
    ],
    "UserData": [
        {
            "Time": 0.0,
            "Value": ""
        }
    ]
}